mask_plus/__init__.py
mask_plus/plus.py
mask_plus-1.0.0.dist-info/METADATA
mask_plus-1.0.0.dist-info/WHEEL
mask_plus-1.0.0.dist-info/entry_points.txt
mask_plus-1.0.0.dist-info/top_level.txt
mask_plus-1.0.0.dist-info/RECORD
