Metadata-Version: 2.1
Name: mask_plus
Version: 1.0.0
Summary: add func added
Author-email: GITSangWoo <dogcenta@gmail.com>
License: MIT
Requires-Python: >=3.8
